wagtail_cache-3.0.0.dist-info/licenses/LICENSE
wagtailcache/__init__.py
wagtailcache/apps.py
wagtailcache/cache.py
wagtailcache/settings.py
wagtailcache/urls.py
wagtailcache/views.py
wagtailcache/wagtail_hooks.py
wagtailcache/management/commands/clear_wagtail_cache.py
wagtailcache/templates/wagtailcache/index.html
wagtailcache/templates/wagtailcache/wagtailcache-bolt.svg
wagtailcache/templatetags/__init__.py
wagtailcache/templatetags/wagtailcache_tags.py
wagtail_cache-3.0.0.dist-info/METADATA
wagtail_cache-3.0.0.dist-info/WHEEL
wagtail_cache-3.0.0.dist-info/top_level.txt
wagtail_cache-3.0.0.dist-info/RECORD
