Metadata-Version: 2.4
Name: wagtail-cache
Version: 3.0.0
Summary: A simple page cache for Wagtail based on the Django cache middleware.
Author-email: CodeRed LLC <info@coderedcorp.com>
License: BSD License
Project-URL: Source, https://github.com/coderedcorp/wagtail-cache
Classifier: Intended Audience :: Developers
Classifier: License :: OSI Approved :: BSD License
Classifier: Natural Language :: English
Classifier: Operating System :: OS Independent
Classifier: Programming Language :: Python :: 3
Classifier: Programming Language :: Python :: 3 :: Only
Classifier: Framework :: Django
Classifier: Framework :: Wagtail
Classifier: Framework :: Wagtail :: 3
Classifier: Framework :: Wagtail :: 4
Classifier: Framework :: Wagtail :: 5
Classifier: Framework :: Wagtail :: 6
Classifier: Framework :: Wagtail :: 7
Requires-Python: >=3.8
License-File: LICENSE
Requires-Dist: wagtail<8.0,>=3.0
Dynamic: license-file
